microbenthos/__init__.py
microbenthos/cli.py
microbenthos/core/__init__.py
microbenthos/core/domain.py
microbenthos/core/entity.py
microbenthos/core/expression.py
microbenthos/core/irradiance.py
microbenthos/core/microbes.py
microbenthos/core/process.py
microbenthos/core/variable.py
microbenthos/dataview/__init__.py
microbenthos/dataview/base.py
microbenthos/dataview/hdfstore.py
microbenthos/dataview/plotter.py
microbenthos/dataview/snapshot.py
microbenthos/exporters/__init__.py
microbenthos/exporters/_output_dir_mixin.py
microbenthos/exporters/exporter.py
microbenthos/exporters/graphic.py
microbenthos/exporters/model_data.py
microbenthos/exporters/progress.py
microbenthos/model/__init__.py
microbenthos/model/equation.py
microbenthos/model/model.py
microbenthos/model/resume.py
microbenthos/model/saver.py
microbenthos/model/simulation.py
microbenthos/runners/__init__.py
microbenthos/runners/simulate.py
microbenthos/utils/__init__.py
microbenthos/utils/create.py
microbenthos/utils/loader.py
microbenthos/utils/log.py
microbenthos/utils/schema.yml
microbenthos/utils/snapshotters.py
microbenthos/utils/yaml_setup.py
microbenthos-0.14.dist-info/AUTHORS.rst
microbenthos-0.14.dist-info/LICENSE
microbenthos-0.14.dist-info/METADATA
microbenthos-0.14.dist-info/WHEEL
microbenthos-0.14.dist-info/entry_points.txt
microbenthos-0.14.dist-info/top_level.txt
microbenthos-0.14.dist-info/RECORD
