Metadata-Version: 2.1
Name: microbenthos
Version: 0.14
Summary: Modeling framework for microbenthic habitats useful for studies in biogeochemistry and marine microbial ecology.
Home-page: https://microbenthos.readthedocs.io
Author: Arjun Chennu
Author-email: arjun.chennu@gmail.com
License: MIT license
Keywords: microbenthos,biogeochemistry,marine biology,microbial ecology,simulation,modeling,microbial mats,sediments
Platform: UNKNOWN
Classifier: Development Status :: 5 - Production/Stable
Classifier: Intended Audience :: Developers
Classifier: License :: OSI Approved :: MIT License
Classifier: Natural Language :: English
Classifier: Programming Language :: Python 
Classifier: Programming Language :: Python :: 3.6
Classifier: Programming Language :: Python :: 3.7
Classifier: Programming Language :: Python :: 3.8
Requires-Dist: click
Requires-Dist: future
Requires-Dist: logutils
Requires-Dist: sympy
Requires-Dist: cerberus
Requires-Dist: PyYaml
Requires-Dist: h5py
Requires-Dist: tqdm
Requires-Dist: matplotlib (>=2.1)
Requires-Dist: scipy
Requires-Dist: numpy
Requires-Dist: fipy
Provides-Extra: docs
Requires-Dist: sphinx ; extra == 'docs'
Requires-Dist: sphinx-rtd-theme ; extra == 'docs'
Requires-Dist: sphinxcontrib-programoutput ; extra == 'docs'
Requires-Dist: sphinx-autodoc-typehints ; extra == 'docs'
Provides-Extra: test
Requires-Dist: pytest ; extra == 'test'
Requires-Dist: mock ; extra == 'test'
